{
  "MajorClaims": {
    "MC1": "it is no evidence about the reduction of crime rates due to the death penalty",
    "MC2": "The world should consider clearly about polishing the law of the dead penalty"
  },
  "Claims": {
    "C1": "death penalty neither controls the violent in society nor creates a violent culture",
    "C2": "nobody has the right to take another human life",
    "C3": "with some of serious criminals, capital punishment is an easy way out",
    "C4": "it neither demines crimes of violence nor be essential to control violence in society"
  },
  "Premises": {
    "P1": "Crimes kill someone which is illegal; nevertheless, the government use law to punish them, which is the same way they sinned but in a legal one",
    "P2": "the criminal is repeated second time",
    "P3": "capital punishment is a form of revenge which creates violent culture",
    "P4": "the rights of life are the basic and vital rights of a human being",
    "P5": "No one has the right to take the life of a human; even if he committed murder",
    "P6": "If you kill a criminal, you become a criminal",
    "P7": "crimes seem to increase due to the capital punishment",
    "P8": "if we think that killing is the best way to solve the problem, it is neither unethical nor immoral",
    "P9": "If they kill someone and end their life by dead without paying for their sins, it is so easy for them",
    "P10": "They do not undergo any pain or misery",
    "P11": "Criminals should be punished for their misdeeds",
    "P12": "capital punishment is a form of legalized revenge, it is an easy way for serious crimes, and nobody has rights to take others life",
    "P13": "rehabilitation and education is also a better way in order to prevent or minimize offensive acts",
    "P14": "Why do not punish them by doing something meaningful for the country- it is better",
    "P15": "some industries such as mining, oil and gas extraction, reclamation, etc, needs many labors",
    "P16": "it is regarded as the \"legalized revenge\" to victims' family"
  },
  "ArgumentativeRelations": [
    {
      "Origin": "C1",
      "Relation": "For",
      "Target": "MC"
    },
    {
      "Origin": "C2",
      "Relation": "For",
      "Target": "MC"
    },
    {
      "Origin": "C4",
      "Relation": "For",
      "Target": "MC"
    },
    {
      "Origin": "C3",
      "Relation": "For",
      "Target": "MC"
    },
    {
      "Origin": "P2",
      "Relation": "supports",
      "Target": "P16"
    },
    {
      "Origin": "P16",
      "Relation": "supports",
      "Target": "C1"
    },
    {
      "Origin": "P1",
      "Relation": "supports",
      "Target": "C1"
    },
    {
      "Origin": "P3",
      "Relation": "supports",
      "Target": "C1"
    },
    {
      "Origin": "P11",
      "Relation": "supports",
      "Target": "C3"
    },
    {
      "Origin": "P9",
      "Relation": "supports",
      "Target": "C3"
    },
    {
      "Origin": "P10",
      "Relation": "supports",
      "Target": "C3"
    },
    {
      "Origin": "P15",
      "Relation": "supports",
      "Target": "C3"
    },
    {
      "Origin": "P14",
      "Relation": "supports",
      "Target": "C3"
    },
    {
      "Origin": "P13",
      "Relation": "supports",
      "Target": "C3"
    },
    {
      "Origin": "P12",
      "Relation": "supports",
      "Target": "C4"
    },
    {
      "Origin": "P5",
      "Relation": "supports",
      "Target": "P4"
    },
    {
      "Origin": "P4",
      "Relation": "supports",
      "Target": "C2"
    },
    {
      "Origin": "P6",
      "Relation": "supports",
      "Target": "C2"
    },
    {
      "Origin": "P8",
      "Relation": "supports",
      "Target": "C2"
    },
    {
      "Origin": "P7",
      "Relation": "supports",
      "Target": "C2"
    }
  ]
}