{
  "MajorClaims": [
    {
      "ID": "MC1",
      "Text": "it is a good idea to build a large shopping center in our community"
    },
    {
      "ID": "MC2",
      "Text": "I advocate building a big shopping center in my neighborhood, which will be beneficial to our community"
    }
  ],
  "Claims": [
    {
      "ID": "C1",
      "Text": "a large shopping mall provides a location for residents to pursue during their leisure time"
    },
    {
      "ID": "C2",
      "Text": "it not only provides a place to shop but also offer people jobs"
    },
    {
      "ID": "C3",
      "Text": "it is more likely for us to buy goods in lower price in the shopping center, and save our time on the other hand"
    }
  ],
  "Premises": [
    {
      "ID": "P1",
      "Text": "the establishment of a large shopping center will provide the residents a more convenient place to go shopping"
    },
    {
      "ID": "P2",
      "Text": "Queens Center Mall, a shopping mall located in Queens borough of New York City, provides a wide vairtey of stores, products and services, from clothing to electronics and restaurants, that consumers can choose"
    },
    {
      "ID": "P3",
      "Text": "it is one of the most productive malls in New York"
    },
    {
      "ID": "P4",
      "Text": "I could find virtually every brand or store, including Macy's and JCPenney, when I visited there"
    },
    {
      "ID": "P5",
      "Text": "There may be a great number of job vacancies in the need of opening the new stores in the shopping mall"
    },
    {
      "ID": "P6",
      "Text": "It could be an opportunity for people who are looking for a part-time job or a full time job"
    },
    {
      "ID": "P7",
      "Text": "Some students and retirees may work there in order to whiling away their free time and earning money"
    },
    {
      "ID": "P8",
      "Text": "There may be a competition between the new shopping center and other existing stores to attract the customers"
    },
    {
      "ID": "P9",
      "Text": "with sales promotion, it is easy for consumers to compare the price of the same merchandise before they buy"
    },
    {
      "ID": "P10",
      "Text": "the residents do not have a problem spending time on commute in the hope of setting up a shopping center near their homes"
    }
  ],
  "ArgumentativeRelations": [
    {
      "Origin": "C1",
      "Relation": "For",
      "Target": "MC"
    },
    {
      "Origin": "P2",
      "Relation": "supports",
      "Target": "C1"
    },
    {
      "Origin": "P3",
      "Relation": "supports",
      "Target": "C1"
    },
    {
      "Origin": "P4",
      "Relation": "supports",
      "Target": "C1"
    },
    {
      "Origin": "C2",
      "Relation": "For",
      "Target": "MC"
    },
    {
      "Origin": "P5",
      "Relation": "supports",
      "Target": "C2"
    },
    {
      "Origin": "P6",
      "Relation": "supports",
      "Target": "C2"
    },
    {
      "Origin": "P7",
      "Relation": "supports",
      "Target": "C2"
    },
    {
      "Origin": "C3",
      "Relation": "For",
      "Target": "MC"
    },
    {
      "Origin": "P8",
      "Relation": "supports",
      "Target": "C3"
    },
    {
      "Origin": "P9",
      "Relation": "supports",
      "Target": "C3"
    },
    {
      "Origin": "P10",
      "Relation": "supports",
      "Target": "C3"
    },
    {
      "Origin": "P1",
      "Relation": "supports",
      "Target": "C1"
    }
  ]
}