{
  "MajorClaims": [
    {
      "ID": "MC1",
      "Text": "I myself agree with the plan to build the university"
    },
    {
      "ID": "MC2",
      "Text": "the benefit from it will outweigh the cost"
    },
    {
      "ID": "MC3",
      "Text": "I will be happy to hear that the government has a plan to build a new university in my community"
    }
  ],
  "Claims": [
    {
      "ID": "C1",
      "Text": "There are many advantages setting up the university such as more opportunities to people in the community to pursue their studies, creation of jobs"
    },
    {
      "ID": "C2",
      "Text": "This new university will allow a great number of people in my community to have a chance to study"
    },
    {
      "ID": "C3",
      "Text": "This can also help stimulate the local economy"
    },
    {
      "ID": "C4",
      "Text": "building the university may lead to some social problems"
    }
  ],
  "Premises": [
    {
      "ID": "P1",
      "Text": "suppose you live in a faraway community where there is no single university and you might not want to leave your family"
    },
    {
      "ID": "P2",
      "Text": "If you would like to attend a business school, you have to travel across the country to get to a distant university"
    },
    {
      "ID": "P3",
      "Text": "He or she definitely can get in the business school in the proposed community's university"
    },
    {
      "ID": "P4",
      "Text": "a number vacant positions need to be filled"
    },
    {
      "ID": "P5",
      "Text": "the university will have to hire professors, employees and etc"
    },
    {
      "ID": "P6",
      "Text": "there will be more opportunities to work in the community"
    },
    {
      "ID": "P7",
      "Text": "when people have jobs, they will have money to spend on goods and services"
    },
    {
      "ID": "P8",
      "Text": "A number of people then may come from any other communities in order to get in to or get the jobs at the university"
    },
    {
      "ID": "P9",
      "Text": "When many people congregate in one place, I think that some kinds of social problems will follow"
    },
    {
      "ID": "P10",
      "Text": "Traffic may worsen"
    },
    {
      "ID": "P11",
      "Text": "More wastes have to be managed"
    },
    {
      "ID": "P12",
      "Text": "Maybe crime rate will also increase"
    },
    {
      "ID": "P13",
      "Text": "These social problems may impair the quality of life in the community"
    }
  ],
  "ArgumentativeRelations": [
    {
      "Origin": "C1",
      "Relation": "For",
      "Target": "MC"
    },
    {
      "Origin": "C2",
      "Relation": "For",
      "Target": "MC"
    },
    {
      "Origin": "P1",
      "Relation": "supports",
      "Target": "C2"
    },
    {
      "Origin": "P2",
      "Relation": "supports",
      "Target": "C2"
    },
    {
      "Origin": "P3",
      "Relation": "supports",
      "Target": "C2"
    },
    {
      "Origin": "P5",
      "Relation": "supports",
      "Target": "P4"
    },
    {
      "Origin": "P6",
      "Relation": "supports",
      "Target": "P4"
    },
    {
      "Origin": "C3",
      "Relation": "For",
      "Target": "MC"
    },
    {
      "Origin": "P4",
      "Relation": "supports",
      "Target": "C3"
    },
    {
      "Origin": "P7",
      "Relation": "supports",
      "Target": "C3"
    },
    {
      "Origin": "C4",
      "Relation": "For",
      "Target": "MC"
    },
    {
      "Origin": "P8",
      "Relation": "supports",
      "Target": "C4"
    },
    {
      "Origin": "P9",
      "Relation": "supports",
      "Target": "C4"
    },
    {
      "Origin": "P10",
      "Relation": "supports",
      "Target": "C4"
    },
    {
      "Origin": "P11",
      "Relation": "supports",
      "Target": "C4"
    },
    {
      "Origin": "P12",
      "Relation": "supports",
      "Target": "C4"
    },
    {
      "Origin": "P13",
      "Relation": "supports",
      "Target": "C4"
    }
  ]
}