{
  "MajorClaims": [
    {
      "ID": "MC1",
      "Text": "I would follow the new customs, if I migrated to another country"
    },
    {
      "ID": "MC2",
      "Text": "the immigrants should follow the customs in the new country"
    }
  ],
  "Claims": [
    {
      "ID": "C1",
      "Text": "it will be easier for people to assimilate into a new country, if they follow the new customs"
    },
    {
      "ID": "C2",
      "Text": "keeping own customs stably might cause discrimination"
    }
  ],
  "Premises": [
    {
      "ID": "P1",
      "Text": "When people migrate to a new country, they are likely to suffer the culture shock, because of the difference between two cultures"
    },
    {
      "ID": "P2",
      "Text": "The custom is just a form of the culture and following the custom is a good way to know more about this culture"
    },
    {
      "ID": "P3",
      "Text": "if one wore in white and went to common Viharas to observe a rather longer-than-usual, full-length Buddhist sutra in Buddha's Birthday in India, he or she would learn something about Indian religion and culture"
    },
    {
      "ID": "P4",
      "Text": "people understand the culture, and then they adapt to the new country"
    },
    {
      "ID": "P5",
      "Text": "When people insist to keep their own customs and refuse to accept the new one, they regard themselves as a special group in the new country"
    },
    {
      "ID": "P6",
      "Text": "The local people may also regard them as a special group as well and separate them from the main-stream society"
    },
    {
      "ID": "P7",
      "Text": "One example of this is that the Chinese immigrants in Indonesia in 1969"
    },
    {
      "ID": "P8",
      "Text": "They formed Chinatown and kept Chinese language and customs in it"
    },
    {
      "ID": "P9",
      "Text": "While the Indonesians stopped working at 4:00 pm and went home for rest, Chinese immigrants were still working"
    },
    {
      "ID": "P10",
      "Text": "being much richer than local people, they faced the discrimination"
    },
    {
      "ID": "P11",
      "Text": "Their houses and private cars were buried by local people"
    },
    {
      "ID": "P12",
      "Text": "the locals were jealous of Chinese people, who had so much wealth, which should have been theirs"
    },
    {
      "ID": "P13",
      "Text": "If the Chinese immigrants had followed the local customs and assimilated into Indonesia, they would not have been regards as a group of Chinese and discrimination might have been alleviated"
    }
  ],
  "ArgumentativeRelations": [
    {
      "Origin": "C1",
      "Relation": "For",
      "Target": "MC"
    },
    {
      "Origin": "C2",
      "Relation": "For",
      "Target": "MC"
    },
    {
      "Origin": "P3",
      "Relation": "supports",
      "Target": "P4"
    },
    {
      "Origin": "P4",
      "Relation": "supports",
      "Target": "C1"
    },
    {
      "Origin": "P1",
      "Relation": "supports",
      "Target": "C1"
    },
    {
      "Origin": "P2",
      "Relation": "supports",
      "Target": "C1"
    },
    {
      "Origin": "P5",
      "Relation": "supports",
      "Target": "C2"
    },
    {
      "Origin": "P6",
      "Relation": "supports",
      "Target": "C2"
    },
    {
      "Origin": "P7",
      "Relation": "supports",
      "Target": "C2"
    },
    {
      "Origin": "P8",
      "Relation": "supports",
      "Target": "C2"
    },
    {
      "Origin": "P9",
      "Relation": "supports",
      "Target": "C2"
    },
    {
      "Origin": "P11",
      "Relation": "supports",
      "Target": "C2"
    },
    {
      "Origin": "P10",
      "Relation": "supports",
      "Target": "C2"
    },
    {
      "Origin": "P13",
      "Relation": "supports",
      "Target": "C2"
    },
    {
      "Origin": "P12",
      "Relation": "supports",
      "Target": "P11"
    }
  ]
}